goodText/__init__.py
goodText/goodText.py
goodText/libs/__init__.py
goodText/libs/__version__.py
goodText/libs/_internal_utils.py
goodText/libs/adapters.py
goodText/libs/api.py
goodText/libs/argparse.py
goodText/libs/auth.py
goodText/libs/certs.py
goodText/libs/compat.py
goodText/libs/config.py
goodText/libs/cookies.py
goodText/libs/exceptions.py
goodText/libs/handlers.py
goodText/libs/help.py
goodText/libs/hooks.py
goodText/libs/models.py
goodText/libs/os.py
goodText/libs/packages.py
goodText/libs/sessions.py
goodText/libs/status_codes.py
goodText/libs/structures.py
goodText/libs/utils.py
goodText-1.0.4.dist-info/LICENSE.txt
goodText-1.0.4.dist-info/METADATA
goodText-1.0.4.dist-info/WHEEL
goodText-1.0.4.dist-info/top_level.txt
goodText-1.0.4.dist-info/RECORD
