Metadata-Version: 2.1
Name: goodText
Version: 1.0.4
Summary: Programa simples de mudança de cor de texto
Home-page: UNKNOWN
Author: Jonatas Miguel
Author-email: jonatas.miguelss@gmail.com
License: UNKNOWN
Keywords: Mudar cor texto
Platform: UNKNOWN
Classifier: Development Status :: 5 - Production/Stable
Classifier: Intended Audience :: Developers
Classifier: License :: OSI Approved :: MIT License
Classifier: Natural Language :: Portuguese (Brazilian)
Classifier: Operating System :: OS Independent
Classifier: Topic :: Software Development :: Internationalization
Classifier: Topic :: Scientific/Engineering :: Physics
License-File: LICENSE.txt
